Workbook

Sheet README
B2: Analytical Study of Ankita Cashew Processing
B3: BDM Capstone — FINAL Analysis Workbook
B4: Akash Jana | Roll 23f2000990 | IIT Madras BS Degree
B6: This workbook supports the FINAL report. Charts embedded here are the SAME images used
B7: in the report (so they match). The script "analysis_final.py" reproduces everything.
B9: Sheets:
B10: Cleaning Log - cleaning counts and examples
B11: Transactions - cleaned ledger (850 rows)
B12: Descriptive Stats - mean/median/SD/min/max for all variables
B13: Annual Summary - year-wise sales vs purchase
B14: Forecast - forecast accuracy (RMSE/MAE)
B15: Yield - yield per cycle, variance, Z-score
... B21: Blue cells = inputs/assumptions; black cells = Excel formulas. Amounts in ₹, weights in KG.

Sheet Cleaning Log
A1: Data Cleaning Log
A3: Step | B3: Count
A4: Cells scanned | B4: 5572
A5: Non-data rows skipped | B5: 4720
A6: Exact duplicates removed | B6: 2
A7: Clean transactions kept | B7: 850
A9: Duplicate examples: ₹70,000 cash sale (Ankita 31-Mar-2023); ₹25,00,000 RCN purchase (Ankita 30-Jul-2024).

Sheet Transactions
A1: Company | B1: Flow | C1: Goods | D1: Date | E1: Counterparty | F1: Amount (₹) | G1: Financial Year
A2: Adrita | B2: Sale | C2: FCN | D2: 44671 | E2: M/s Shree Taran Traders | F2: 243628 | G2: FY22-23
A3: Adrita | B3: Sale | C3: FCN | D3: 44677 | E3: ASHWANI KUMAR NEEL KAMAL | F3: 526073 | G3: FY22-23
A4: Adrita | B4: Purchase | C4: RCN | D4: 44688 | E4: VIJAY TRADERS | F4: 1683200 | G4: FY22-23
A5: Adrita | B5: Sale | C5: FCN | D5: 44698 | E5: M/S RADHYSHYAM SAMBHUNATH | F5: 302860 | G5: FY22-23
A6: Adrita | B6: Sale | C6: FCN | D6: 44705 | E6: M/S PADAM & SONS | F6: 980712 | G6: FY22-23
A7: Adrita | B7: Purchase | C7: RCN | D7: 44710 | E7: Maa Laxmi Cashew | F7: 732947.2 | G7: FY22-23
A8: Adrita | B8: Sale | C8: FCN | D8: 44725 | E8: ASHWANI KUMAR NEEL KAMAL | F8: 910585 | G8: FY22-23
A9: Adrita | B9: Purchase | C9: RCN | D9: 44729 | E9: Durga Cashew Co | F9: 552619.05 | G9: FY22-23
A10: Adrita | B10: Sale | C10: FCN | D10: 44734 | E10: Subham Traders | F10: 892778 | G10: FY22-23
A11: Adrita | B11: Purchase | C11: RCN | D11: 44741 | E11: Durga Cashew Co | F11: 490476.19 | G11: FY22-23
A12: Adrita | B12: Purchase | C12: RCN | D12: 44741 | E12: Ankita Cashew Processing | F12: 4000000 | G12: FY22-23
A13: Adrita | B13: Sale | C13: RCN | D13: 44742 | E13: Nandi Cashew Processing | F13: 1718080 | G13: FY22-23
... A851: Ankita | B851: Purchase | C851: RCN | D851: 46057 | E851: Ahana Enterprises | F851: 3981570 | G851: FY25-26

Sheet Descriptive Stats
A1: Descriptive Statistics — all variables
A3: Variable | B3: Count | C3: Mean | D3: Median | E3: SD | F3: Min | G3: Max
A4: Sale amount (₹) | B4: 578 | C4: 514839 | D4: 349333 | E4: 511815 | F4: 10476 | G4: 4000000
A5: Purchase amount (₹) | B5: 272 | C5: 995213 | D5: 565386 | E5: 1082649 | F5: 1907 | G5: 5041701
A6: RCN price (₹/KG) | B6: 79 | C6: 126.5 | D6: 120 | E6: 25.3 | F6: 89 | G6: 179.1
A7: Buyer revenue (₹) | B7: 130 | C7: 2272582 | D7: 893287 | E7: 4303064 | F7: 10476 | G7: 30087807
A8: Buyer orders (count) | B8: 130 | C8: 4.3 | D8: 2 | E8: 6 | F8: 1 | G8: 36
A9: Buyer risk score (0-100) | B9: 130 | C9: 55.7 | D9: 54.8 | E9: 13.6 | F9: 27.8 | G9: 100
A10: Contribution per kg kernel (₹) | B10: 3 | C10: 80.1 | D10: 119.9 | E10: 173.5 | F10: -109.8 | G10: 230.2

Sheet Annual Summary
A1: Annual Sales vs Purchase
A3: Financial Year | B3: Sales (₹) | C3: Purchase (₹) | D3: Net (₹)
A4: FY22-23 | B4: 72524077 | C4: 73780058 | D4: =B4-C4 -> -1255981
A5: FY23-24 | B5: 76227072 | C5: 68141555 | D5: =B5-C5 -> 8085517
A6: FY24-25 | B6: 81086538 | C6: 70636908 | D6: =B6-C6 -> 10449630
A7: FY25-26 | B7: 67738985 | C7: 58139303 | D7: =B7-C7 -> 9599682

Sheet Forecast
A1: Forecast Accuracy (6-month holdout)
A3: Model | B3: RMSE (₹) | C3: MAE (₹)
A4: ARIMA | B4: 2527935 | C4: 2167929
A5: Linear (base) | B5: 2181363 | C5: 1929917
A6: Naive | B6: 4304027 | C6: 3028328

Sheet Yield
A1: Yield per Cycle
A3: Cycle | B3: Yield % | C3: Variance | D3: Z-score | E3: Outlier
A4: Adrita FY22-23 | B4: 17.4 | C4: -4.6 | D4: -0.22 | E4: No
A5: Adrita FY23-24 | B5: 20.2 | C5: -1.8 | D5: 0.39 | E5: No
A6: Adrita FY24-25 | B6: 22.8 | C6: 0.8 | D6: 0.95 | E6: No
A7: Adrita FY25-26 | B7: 19.8 | C7: -2.2 | D7: 0.29 | E7: No
A8: Ankita FY22-23 | B8: 10.8 | C8: -11.2 | D8: -1.66 | E8: Yes
A9: Ankita FY23-24 | B9: 17.8 | C9: -4.2 | D9: -0.16 | E9: No
A10: Ankita FY24-25 | B10: 13.9 | C10: -8.1 | D10: -1 | E10: No
A11: Ankita FY25-26 | B11: 25 | C11: 3 | D11: 1.42 | E11: No

Sheet P&L Model
A1: Profit & Loss — Live Contribution Model
A2: Edit the blue assumption cells to test scenarios. Black cells are formulas.
A4: Assumptions
A5: RCN price (₹/kg) | B5: 123.2
A6: Outturn / yield | B6: 0.22
A7: Processing & overhead (₹/kg kernel) | B7: 30
A8: Kernel selling price (₹/kg) | B8: 709.8
A10: Computed
A11: Raw nut cost per kg kernel | B11: =B5/B6 -> 560
A12: Total cost per kg kernel | B12: =B11+B7 -> 590
A13: Contribution per kg kernel | B13: =B8-B12 -> 119.8
A14: Margin % | B14: =B13/B8 -> 0.16877994
A15: Break-even price (₹/kg) | B15: =B12 -> 590
A16: Break-even outturn | B16: =B5/(B8-B7) -> 0.18122977
A18: By grade
A19: Grade | B19: Price (₹/kg) | C19: Contribution (₹/kg)
A20: Whole | B20: 820 | C20: =B20-B12 -> 230
A21: Broken | B21: 480 | C21: =B21-B12 -> -110

Sheet Sensitivity
A1: Contribution Sensitivity (₹/kg kernel)
A2: Rows = RCN price change, Columns = selling-price change. Live formulas off 'P&L Model'.
A4: RCN ↓ / Price → | B4: -10% | C4: -5% | D4: +0% | E4: +5% | F4: +10%
A5: -10% | B5: ='P&L Model'!$B$8*(1+-0.1)-('P&L Model'!$B$5*(1+-0.1)/'P&L Model'!$B$6+'P&L Model'!$B$7) -> 104.82 | C5: ='P&L Model'!$B$8*(1+-0.05)-('P&L Model'!$B$5*(1+-0.1)/'P&L Model'!$B$6+'P&L Model'!$B$7) -> 140.31 | D5: ='P&L Model'!$B$8*(1+0)-('P&L Model'!$B$5*(1+-0.1)/'P&L Model'!$B$6+'P&L Model'!$B$7) -> 175.8 | E5: ='P&L Model'!$B$8*(1+0.05)-('P&L Model'!$B$5*(1+-0.1)/'P&L Model'!$B$6+'P&L Model'!$B$7) -> 211.29 | F5: ='P&L Model'!$B$8*(1+0.1)-('P&L Model'!$B$5*(1+-0.1)/'P&L Model'!$B$6+'P&L Model'!$B$7) -> 246.78
A6: -5% | B6: ='P&L Model'!$B$8*(1+-0.1)-('P&L Model'!$B$5*(1+-0.05)/'P&L Model'!$B$6+'P&L Model'!$B$7) -> 76.82 | C6: ='P&L Model'!$B$8*(1+-0.05)-('P&L Model'!$B$5*(1+-0.05)/'P&L Model'!$B$6+'P&L Model'!$B$7) -> 112.31 | D6: ='P&L Model'!$B$8*(1+0)-('P&L Model'!$B$5*(1+-0.05)/'P&L Model'!$B$6+'P&L Model'!$B$7) -> 147.8 | E6: ='P&L Model'!$B$8*(1+0.05)-('P&L Model'!$B$5*(1+-0.05)/'P&L Model'!$B$6+'P&L Model'!$B$7) -> 183.29 | F6: ='P&L Model'!$B$8*(1+0.1)-('P&L Model'!$B$5*(1+-0.05)/'P&L Model'!$B$6+'P&L Model'!$B$7) -> 218.78
A7: +0% | B7: ='P&L Model'!$B$8*(1+-0.1)-('P&L Model'!$B$5*(1+0)/'P&L Model'!$B$6+'P&L Model'!$B$7) -> 48.82 | C7: ='P&L Model'!$B$8*(1+-0.05)-('P&L Model'!$B$5*(1+0)/'P&L Model'!$B$6+'P&L Model'!$B$7) -> 84.31 | D7: ='P&L Model'!$B$8*(1+0)-('P&L Model'!$B$5*(1+0)/'P&L Model'!$B$6+'P&L Model'!$B$7) -> 119.8 | E7: ='P&L Model'!$B$8*(1+0.05)-('P&L Model'!$B$5*(1+0)/'P&L Model'!$B$6+'P&L Model'!$B$7) -> 155.29 | F7: ='P&L Model'!$B$8*(1+0.1)-('P&L Model'!$B$5*(1+0)/'P&L Model'!$B$6+'P&L Model'!$B$7) -> 190.78
A8: +5% | B8: ='P&L Model'!$B$8*(1+-0.1)-('P&L Model'!$B$5*(1+0.05)/'P&L Model'!$B$6+'P&L Model'!$B$7) -> 20.82 | C8: ='P&L Model'!$B$8*(1+-0.05)-('P&L Model'!$B$5*(1+0.05)/'P&L Model'!$B$6+'P&L Model'!$B$7) -> 56.31 | D8: ='P&L Model'!$B$8*(1+0)-('P&L Model'!$B$5*(1+0.05)/'P&L Model'!$B$6+'P&L Model'!$B$7) -> 91.8 | E8: ='P&L Model'!$B$8*(1+0.05)-('P&L Model'!$B$5*(1+0.05)/'P&L Model'!$B$6+'P&L Model'!$B$7) -> 127.29 | F8: ='P&L Model'!$B$8*(1+0.1)-('P&L Model'!$B$5*(1+0.05)/'P&L Model'!$B$6+'P&L Model'!$B$7) -> 162.78
A9: +10% | B9: ='P&L Model'!$B$8*(1+-0.1)-('P&L Model'!$B$5*(1+0.1)/'P&L Model'!$B$6+'P&L Model'!$B$7) -> -7.18 | C9: ='P&L Model'!$B$8*(1+-0.05)-('P&L Model'!$B$5*(1+0.1)/'P&L Model'!$B$6+'P&L Model'!$B$7) -> 28.31 | D9: ='P&L Model'!$B$8*(1+0)-('P&L Model'!$B$5*(1+0.1)/'P&L Model'!$B$6+'P&L Model'!$B$7) -> 63.8 | E9: ='P&L Model'!$B$8*(1+0.05)-('P&L Model'!$B$5*(1+0.1)/'P&L Model'!$B$6+'P&L Model'!$B$7) -> 99.29 | F9: ='P&L Model'!$B$8*(1+0.1)-('P&L Model'!$B$5*(1+0.1)/'P&L Model'!$B$6+'P&L Model'!$B$7) -> 134.78

Sheet Buyer Scorecard
A1: Buyer Risk Scorecard
A3: Tier | B3: Buyers | C3: Credit exposure (₹)
A4: Low | B4: 7 | C4: 14125000
A5: Medium | B5: 90 | C5: 44005000
A6: High | B6: 33 | C6: 8961000
A8: Illustrative logistic model: AUC=0.96, accuracy=0.923 (simulated delays — see report).
A10: Top buyers
A11: Buyer | B11: Revenue (₹) | C11: Orders | D11: Recency (d) | E11: Risk | F11: Tier | G11: Credit limit (₹)
A12: ASHWANI KUMAR NEEL KAMAL | B12: 30087807 | C12: 26 | D12: 18 | E12: 29.6 | F12: Low | G12: 2616000
A13: Maa Laxmi Cashew Processing | B13: 24082072 | C13: 13 | D13: 470 | E13: 51.4 | F13: Medium | G13: 2189000
A14: M/s Ashwani Kumar Neel Kamal | B14: 20570081 | C14: 19 | D14: 83 | E14: 30.9 | F14: Low | G14: 2571000
A15: DEVIDEEN HANUMANPRASAD | B15: 17125429 | C15: 33 | D15: 45 | E15: 31.1 | F15: Low | G15: 1489000
A16: Satyam Traders | B16: 10391863 | C16: 16 | D16: 524 | E16: 44.9 | F16: Medium | G16: 1039000
A17: Nandi Cashew Processing | B17: 10064274 | C17: 7 | D17: 615 | E17: 58.1 | F17: Medium | G17: 1438000
A18: Shree Taran Traders | B18: 7999480 | C18: 36 | D18: 301 | E18: 34.5 | F18: Medium | G18: 308000
A19: P P Enterprises | B19: 7725387 | C19: 26 | D19: 208 | E19: 30.4 | F19: Low | G19: 858000
A20: Sashwat Traders | B20: 7561262 | C20: 11 | D20: 497 | E20: 45.1 | F20: Medium | G20: 945000
A21: Ramesh Chand Naresh Kumar | B21: 7119041 | C21: 22 | D21: 31 | E21: 27.9 | F21: Low | G21: 1187000
A22: DEB TRADERS | B22: 5692491 | C22: 6 | D22: 222 | E22: 43.5 | F22: Medium | G22: 949000
A23: M/s Devideen Hanuman Prasad | B23: 5687173 | C23: 13 | D23: 389 | E23: 43.9 | F23: Medium | G23: 632000
... A26: M/s Nandi Cashew Processing | B26: 4715780 | C26: 3 | D26: 1175 | E26: 81.2 | F26: High | G26: 629000

Sheet Anomalies
A1: Anomaly Detection
A3: Flagged 29 of 850 transactions (3.4%): 12 by Z-score, 17 by Isolation Forest. Reconciliation flagged 3 months.
A5: Date | B5: Company | C5: Flow | D5: Goods | E5: Party | F5: Amount (₹) | G5: Z | H5: Flagged by
A6: 2022-11-19 | B6: Ankita | C6: Purchase | D6: RCN | E6: New Kumudini Radio | F6: 1907 | G6: -0.92 | H6: Isolation Forest
A7: 2023-11-03 | B7: Adrita | C7: Purchase | D7: RCN | E7: SUNRICE CHEMICALS PVT LT | F7: 20861 | G7: -1.03 | H7: Isolation Forest
A8: 2023-03-29 | B8: Ankita | C8: Purchase | D8: RCN | E8: SUNRICE CHEMICALS PVT LT | F8: 3035 | G8: -0.91 | H8: Isolation Forest
A9: 2023-02-06 | B9: Ankita | C9: Purchase | D9: RCN | E9: D K Day & Sarker & Co | F9: 10000 | G9: -0.91 | H9: Isolation Forest
A10: 2024-04-15 | B10: Ankita | C10: Purchase | D10: FCN | E10: SUSHMA INDUSTRIES | F10: 43000 | G10: -1.38 | H10: Isolation Forest
A11: 2023-09-03 | B11: Ankita | C11: Purchase | D11: FCN | E11: DEVI CASHEW PROCESSING | F11: 47619 | G11: -1.37 | H11: Isolation Forest
A12: 2025-09-22 | B12: Adrita | C12: Purchase | D12: FCN | E12: MAA CHANDI CASHEW NUT PR | F12: 51900 | G12: -1.2 | H12: Isolation Forest
A13: 2023-12-01 | B13: Ankita | C13: Sale | D13: RCN | E13: Maa Laxmi Cashew Process | F13: 3021429 | G13: 2.39 | H13: Isolation Forest
A14: 2023-12-09 | B14: Ankita | C14: Sale | D14: FCN | E14: CHANDAN PURAKAYATWA | F14: 14286 | G14: -1.01 | H14: Isolation Forest
A15: 2023-05-05 | B15: Adrita | C15: Purchase | D15: RCN | E15: SUNRICE CHEMICALS PVT LT | F15: 17524 | G15: -1.03 | H15: Isolation Forest
A16: 2022-05-10 | B16: Ankita | C16: Purchase | D16: RCN | E16: CHAKADOLA POLYMERS PVT L | F16: 14578 | G16: -0.91 | H16: Isolation Forest
A17: 2025-12-29 | B17: Adrita | C17: Purchase | D17: FCN | E17: Shoel Cashew Processing | F17: 285714 | G17: -0.54 | H17: Isolation Forest
